{".class":"MypyFile","_fullname":"app.models.camera.arlo_models","future_import_flags":[],"is_partial_stub_package":false,"is_stub":false,"names":{".class":"SymbolTable","ArloBaseStation":{".class":"SymbolTableNode","kind":"Gdef","node":{".class":"TypeInfo","_promote":[],"abstract_attributes":[],"alt_promote":null,"bases":["app.models.camera.mixins.TimestampMixin"],"dataclass_transform_spec":null,"declared_metaclass":null,"defn":{".class":"ClassDef","fullname":"app.models.camera.arlo_models.ArloBaseStation","name":"ArloBaseStation","type_vars":[]},"deletable_attributes":[],"deprecated":null,"flags":["fallback_to_any"],"fullname":"app.models.camera.arlo_models.ArloBaseStation","has_param_spec_type":false,"metaclass_type":null,"metadata":{},"module_name":"app.models.camera.arlo_models","mro":["app.models.camera.arlo_models.ArloBaseStation","app.models.camera.mixins.TimestampMixin","builtins.object"],"names":{".class":"SymbolTable","__tablename__":{".class":"SymbolTableNode","kind":"Mdef","node":{".class":"Var","flags":["is_initialized_in_class","is_ready","is_inferred","has_explicit_value"],"fullname":"app.models.camera.arlo_models.ArloBaseStation.__tablename__","name":"__tablename__","setter_type":null,"type":"builtins.str"}},"cameras":{".class":"SymbolTableNode","kind":"Mdef","node":{".class":"Var","flags":["is_initialized_in_class","is_ready","is_inferred","has_explicit_value"],"fullname":"app.models.camera.arlo_models.ArloBaseStation.cameras","name":"cameras","setter_type":null,"type":{".class":"Instance","args":[{".class":"AnyType","missing_import_name":null,"source_any":null,"type_of_any":2}],"extra_attrs":null,"type_ref":"sqlalchemy.orm.relationships._RelationshipDeclared"}}},"credentials_encrypted":{".class":"SymbolTableNode","kind":"Mdef","node":{".class":"Var","flags":["is_initialized_in_class","is_ready","is_inferred","has_explicit_value"],"fullname":"app.models.camera.arlo_models.ArloBaseStation.credentials_encrypted","name":"credentials_encrypted","setter_type":null,"type":{".class":"Instance","args":["builtins.str"],"extra_attrs":null,"type_ref":"sqlalchemy.sql.schema.Column"}}},"id":{".class":"SymbolTableNode","kind":"Mdef","node":{".class":"Var","flags":["is_initialized_in_class","is_ready","is_inferred","has_explicit_value"],"fullname":"app.models.camera.arlo_models.ArloBaseStation.id","name":"id","setter_type":null,"type":{".class":"Instance","args":["builtins.int"],"extra_attrs":null,"type_ref":"sqlalchemy.sql.schema.Column"}}},"ip_address":{".class":"SymbolTableNode","kind":"Mdef","node":{".class":"Var","flags":["is_initialized_in_class","is_ready","is_inferred","has_explicit_value"],"fullname":"app.models.camera.arlo_models.ArloBaseStation.ip_address","name":"ip_address","setter_type":null,"type":{".class":"Instance","args":["builtins.str"],"extra_attrs":null,"type_ref":"sqlalchemy.sql.schema.Column"}}},"last_sync":{".class":"SymbolTableNode","kind":"Mdef","node":{".class":"Var","flags":["is_initialized_in_class","is_ready","is_inferred","has_explicit_value"],"fullname":"app.models.camera.arlo_models.ArloBaseStation.last_sync","name":"last_sync","setter_type":null,"type":{".class":"Instance","args":["datetime.datetime"],"extra_attrs":null,"type_ref":"sqlalchemy.sql.schema.Column"}}},"name":{".class":"SymbolTableNode","kind":"Mdef","node":{".class":"Var","flags":["is_initialized_in_class","is_ready","is_inferred","has_explicit_value"],"fullname":"app.models.camera.arlo_models.ArloBaseStation.name","name":"name","setter_type":null,"type":{".class":"Instance","args":["builtins.str"],"extra_attrs":null,"type_ref":"sqlalchemy.sql.schema.Column"}}},"serial_number":{".class":"SymbolTableNode","kind":"Mdef","node":{".class":"Var","flags":["is_initialized_in_class","is_ready","is_inferred","has_explicit_value"],"fullname":"app.models.camera.arlo_models.ArloBaseStation.serial_number","name":"serial_number","setter_type":null,"type":{".class":"Instance","args":["builtins.str"],"extra_attrs":null,"type_ref":"sqlalchemy.sql.schema.Column"}}},"status":{".class":"SymbolTableNode","kind":"Mdef","node":{".class":"Var","flags":["is_initialized_in_class","is_ready","is_inferred","has_explicit_value"],"fullname":"app.models.camera.arlo_models.ArloBaseStation.status","name":"status","setter_type":null,"type":{".class":"Instance","args":[{".class":"AnyType","missing_import_name":null,"source_any":null,"type_of_any":5}],"extra_attrs":null,"type_ref":"sqlalchemy.sql.schema.Column"}}},"to_dict":{".class":"SymbolTableNode","kind":"Mdef","node":{".class":"FuncDef","abstract_status":0,"arg_kinds":[0],"arg_names":["self"],"dataclass_transform_spec":null,"deprecated":null,"flags":[],"fullname":"app.models.camera.arlo_models.ArloBaseStation.to_dict","name":"to_dict","original_first_arg":"self","type":null}}},"self_type":{".class":"TypeVarType","default":{".class":"AnyType","missing_import_name":null,"source_any":null,"type_of_any":4},"fullname":"app.models.camera.arlo_models.ArloBaseStation.Self","id":0,"name":"Self","namespace":"","upper_bound":"app.models.camera.arlo_models.ArloBaseStation","values":[],"variance":0},"slots":null,"tuple_type":null,"type_vars":[],"typeddict_type":null}},"ArloCamera":{".class":"SymbolTableNode","kind":"Gdef","node":{".class":"TypeInfo","_promote":[],"abstract_attributes":[],"alt_promote":null,"bases":["app.models.camera.mixins.TimestampMixin"],"dataclass_transform_spec":null,"declared_metaclass":null,"defn":{".class":"ClassDef","fullname":"app.models.camera.arlo_models.ArloCamera","name":"ArloCamera","type_vars":[]},"deletable_attributes":[],"deprecated":null,"flags":["fallback_to_any"],"fullname":"app.models.camera.arlo_models.ArloCamera","has_param_spec_type":false,"metaclass_type":null,"metadata":{},"module_name":"app.models.camera.arlo_models","mro":["app.models.camera.arlo_models.ArloCamera","app.models.camera.mixins.TimestampMixin","builtins.object"],"names":{".class":"SymbolTable","__table_args__":{".class":"SymbolTableNode","kind":"Mdef","node":{".class":"Var","flags":["is_initialized_in_class","is_ready","is_inferred","has_explicit_value"],"fullname":"app.models.camera.arlo_models.ArloCamera.__table_args__","name":"__table_args__","setter_type":null,"type":{".class":"TupleType","implicit":false,"items":["sqlalchemy.sql.schema.Index","sqlalchemy.sql.schema.Index","sqlalchemy.sql.schema.Index"],"partial_fallback":{".class":"Instance","args":[{".class":"AnyType","missing_import_name":null,"source_any":null,"type_of_any":6}],"extra_attrs":null,"type_ref":"builtins.tuple"}}}},"__tablename__":{".class":"SymbolTableNode","kind":"Mdef","node":{".class":"Var","flags":["is_initialized_in_class","is_ready","is_inferred","has_explicit_value"],"fullname":"app.models.camera.arlo_models.ArloCamera.__tablename__","name":"__tablename__","setter_type":null,"type":"builtins.str"}},"base_station":{".class":"SymbolTableNode","kind":"Mdef","node":{".class":"Var","flags":["is_initialized_in_class","is_ready","is_inferred","has_explicit_value"],"fullname":"app.models.camera.arlo_models.ArloCamera.base_station","name":"base_station","setter_type":null,"type":{".class":"Instance","args":[{".class":"AnyType","missing_import_name":null,"source_any":null,"type_of_any":2}],"extra_attrs":null,"type_ref":"sqlalchemy.orm.relationships._RelationshipDeclared"}}},"base_station_id":{".class":"SymbolTableNode","kind":"Mdef","node":{".class":"Var","flags":["is_initialized_in_class","is_ready","is_inferred","has_explicit_value"],"fullname":"app.models.camera.arlo_models.ArloCamera.base_station_id","name":"base_station_id","setter_type":null,"type":{".class":"Instance","args":["builtins.int"],"extra_attrs":null,"type_ref":"sqlalchemy.sql.schema.Column"}}},"battery_level":{".class":"SymbolTableNode","kind":"Mdef","node":{".class":"Var","flags":["is_initialized_in_class","is_ready","is_inferred","has_explicit_value"],"fullname":"app.models.camera.arlo_models.ArloCamera.battery_level","name":"battery_level","setter_type":null,"type":{".class":"Instance","args":["builtins.int"],"extra_attrs":null,"type_ref":"sqlalchemy.sql.schema.Column"}}},"device_id":{".class":"SymbolTableNode","kind":"Mdef","node":{".class":"Var","flags":["is_initialized_in_class","is_ready","is_inferred","has_explicit_value"],"fullname":"app.models.camera.arlo_models.ArloCamera.device_id","name":"device_id","setter_type":null,"type":{".class":"Instance","args":["builtins.str"],"extra_attrs":null,"type_ref":"sqlalchemy.sql.schema.Column"}}},"device_type":{".class":"SymbolTableNode","kind":"Mdef","node":{".class":"Var","flags":["is_initialized_in_class","is_ready","is_inferred","has_explicit_value"],"fullname":"app.models.camera.arlo_models.ArloCamera.device_type","name":"device_type","setter_type":null,"type":{".class":"Instance","args":["builtins.str"],"extra_attrs":null,"type_ref":"sqlalchemy.sql.schema.Column"}}},"events":{".class":"SymbolTableNode","kind":"Mdef","node":{".class":"Var","flags":["is_initialized_in_class","is_ready","is_inferred","has_explicit_value"],"fullname":"app.models.camera.arlo_models.ArloCamera.events","name":"events","setter_type":null,"type":{".class":"Instance","args":[{".class":"AnyType","missing_import_name":null,"source_any":null,"type_of_any":2}],"extra_attrs":null,"type_ref":"sqlalchemy.orm.relationships._RelationshipDeclared"}}},"id":{".class":"SymbolTableNode","kind":"Mdef","node":{".class":"Var","flags":["is_initialized_in_class","is_ready","is_inferred","has_explicit_value"],"fullname":"app.models.camera.arlo_models.ArloCamera.id","name":"id","setter_type":null,"type":{".class":"Instance","args":["builtins.int"],"extra_attrs":null,"type_ref":"sqlalchemy.sql.schema.Column"}}},"is_armed":{".class":"SymbolTableNode","kind":"Mdef","node":{".class":"Var","flags":["is_initialized_in_class","is_ready","is_inferred","has_explicit_value"],"fullname":"app.models.camera.arlo_models.ArloCamera.is_armed","name":"is_armed","setter_type":null,"type":{".class":"Instance","args":["builtins.bool"],"extra_attrs":null,"type_ref":"sqlalchemy.sql.schema.Column"}}},"name":{".class":"SymbolTableNode","kind":"Mdef","node":{".class":"Var","flags":["is_initialized_in_class","is_ready","is_inferred","has_explicit_value"],"fullname":"app.models.camera.arlo_models.ArloCamera.name","name":"name","setter_type":null,"type":{".class":"Instance","args":["builtins.str"],"extra_attrs":null,"type_ref":"sqlalchemy.sql.schema.Column"}}},"recordings":{".class":"SymbolTableNode","kind":"Mdef","node":{".class":"Var","flags":["is_initialized_in_class","is_ready","is_inferred","has_explicit_value"],"fullname":"app.models.camera.arlo_models.ArloCamera.recordings","name":"recordings","setter_type":null,"type":{".class":"Instance","args":[{".class":"AnyType","missing_import_name":null,"source_any":null,"type_of_any":2}],"extra_attrs":null,"type_ref":"sqlalchemy.orm.relationships._RelationshipDeclared"}}},"signal_strength":{".class":"SymbolTableNode","kind":"Mdef","node":{".class":"Var","flags":["is_initialized_in_class","is_ready","is_inferred","has_explicit_value"],"fullname":"app.models.camera.arlo_models.ArloCamera.signal_strength","name":"signal_strength","setter_type":null,"type":{".class":"Instance","args":["builtins.int"],"extra_attrs":null,"type_ref":"sqlalchemy.sql.schema.Column"}}},"status":{".class":"SymbolTableNode","kind":"Mdef","node":{".class":"Var","flags":["is_initialized_in_class","is_ready","is_inferred","has_explicit_value"],"fullname":"app.models.camera.arlo_models.ArloCamera.status","name":"status","setter_type":null,"type":{".class":"Instance","args":[{".class":"AnyType","missing_import_name":null,"source_any":null,"type_of_any":5}],"extra_attrs":null,"type_ref":"sqlalchemy.sql.schema.Column"}}},"to_dict":{".class":"SymbolTableNode","kind":"Mdef","node":{".class":"FuncDef","abstract_status":0,"arg_kinds":[0],"arg_names":["self"],"dataclass_transform_spec":null,"deprecated":null,"flags":[],"fullname":"app.models.camera.arlo_models.ArloCamera.to_dict","name":"to_dict","original_first_arg":"self","type":null}}},"self_type":{".class":"TypeVarType","default":{".class":"AnyType","missing_import_name":null,"source_any":null,"type_of_any":4},"fullname":"app.models.camera.arlo_models.ArloCamera.Self","id":0,"name":"Self","namespace":"","upper_bound":"app.models.camera.arlo_models.ArloCamera","values":[],"variance":0},"slots":null,"tuple_type":null,"type_vars":[],"typeddict_type":null}},"ArloEvent":{".class":"SymbolTableNode","kind":"Gdef","node":{".class":"TypeInfo","_promote":[],"abstract_attributes":[],"alt_promote":null,"bases":["app.models.camera.mixins.TimestampMixin"],"dataclass_transform_spec":null,"declared_metaclass":null,"defn":{".class":"ClassDef","fullname":"app.models.camera.arlo_models.ArloEvent","name":"ArloEvent","type_vars":[]},"deletable_attributes":[],"deprecated":null,"flags":["fallback_to_any"],"fullname":"app.models.camera.arlo_models.ArloEvent","has_param_spec_type":false,"metaclass_type":null,"metadata":{},"module_name":"app.models.camera.arlo_models","mro":["app.models.camera.arlo_models.ArloEvent","app.models.camera.mixins.TimestampMixin","builtins.object"],"names":{".class":"SymbolTable","__table_args__":{".class":"SymbolTableNode","kind":"Mdef","node":{".class":"Var","flags":["is_initialized_in_class","is_ready","is_inferred","has_explicit_value"],"fullname":"app.models.camera.arlo_models.ArloEvent.__table_args__","name":"__table_args__","setter_type":null,"type":{".class":"TupleType","implicit":false,"items":["sqlalchemy.sql.schema.Index","sqlalchemy.sql.schema.Index","sqlalchemy.sql.schema.Index"],"partial_fallback":{".class":"Instance","args":[{".class":"AnyType","missing_import_name":null,"source_any":null,"type_of_any":6}],"extra_attrs":null,"type_ref":"builtins.tuple"}}}},"__tablename__":{".class":"SymbolTableNode","kind":"Mdef","node":{".class":"Var","flags":["is_initialized_in_class","is_ready","is_inferred","has_explicit_value"],"fullname":"app.models.camera.arlo_models.ArloEvent.__tablename__","name":"__tablename__","setter_type":null,"type":"builtins.str"}},"camera":{".class":"SymbolTableNode","kind":"Mdef","node":{".class":"Var","flags":["is_initialized_in_class","is_ready","is_inferred","has_explicit_value"],"fullname":"app.models.camera.arlo_models.ArloEvent.camera","name":"camera","setter_type":null,"type":{".class":"Instance","args":[{".class":"AnyType","missing_import_name":null,"source_any":null,"type_of_any":2}],"extra_attrs":null,"type_ref":"sqlalchemy.orm.relationships._RelationshipDeclared"}}},"camera_id":{".class":"SymbolTableNode","kind":"Mdef","node":{".class":"Var","flags":["is_initialized_in_class","is_ready","is_inferred","has_explicit_value"],"fullname":"app.models.camera.arlo_models.ArloEvent.camera_id","name":"camera_id","setter_type":null,"type":{".class":"Instance","args":["builtins.int"],"extra_attrs":null,"type_ref":"sqlalchemy.sql.schema.Column"}}},"details":{".class":"SymbolTableNode","kind":"Mdef","node":{".class":"Var","flags":["is_initialized_in_class","is_ready","is_inferred","has_explicit_value"],"fullname":"app.models.camera.arlo_models.ArloEvent.details","name":"details","setter_type":null,"type":{".class":"Instance","args":[{".class":"AnyType","missing_import_name":null,"source_any":{".class":"AnyType","missing_import_name":null,"source_any":null,"type_of_any":2},"type_of_any":7}],"extra_attrs":null,"type_ref":"sqlalchemy.sql.schema.Column"}}},"event_type":{".class":"SymbolTableNode","kind":"Mdef","node":{".class":"Var","flags":["is_initialized_in_class","is_ready","is_inferred","has_explicit_value"],"fullname":"app.models.camera.arlo_models.ArloEvent.event_type","name":"event_type","setter_type":null,"type":{".class":"Instance","args":[{".class":"AnyType","missing_import_name":null,"source_any":null,"type_of_any":5}],"extra_attrs":null,"type_ref":"sqlalchemy.sql.schema.Column"}}},"id":{".class":"SymbolTableNode","kind":"Mdef","node":{".class":"Var","flags":["is_initialized_in_class","is_ready","is_inferred","has_explicit_value"],"fullname":"app.models.camera.arlo_models.ArloEvent.id","name":"id","setter_type":null,"type":{".class":"Instance","args":["builtins.int"],"extra_attrs":null,"type_ref":"sqlalchemy.sql.schema.Column"}}},"timestamp":{".class":"SymbolTableNode","kind":"Mdef","node":{".class":"Var","flags":["is_initialized_in_class","is_ready","is_inferred","has_explicit_value"],"fullname":"app.models.camera.arlo_models.ArloEvent.timestamp","name":"timestamp","setter_type":null,"type":{".class":"Instance","args":["datetime.datetime"],"extra_attrs":null,"type_ref":"sqlalchemy.sql.schema.Column"}}},"to_dict":{".class":"SymbolTableNode","kind":"Mdef","node":{".class":"FuncDef","abstract_status":0,"arg_kinds":[0],"arg_names":["self"],"dataclass_transform_spec":null,"deprecated":null,"flags":[],"fullname":"app.models.camera.arlo_models.ArloEvent.to_dict","name":"to_dict","original_first_arg":"self","type":null}}},"self_type":{".class":"TypeVarType","default":{".class":"AnyType","missing_import_name":null,"source_any":null,"type_of_any":4},"fullname":"app.models.camera.arlo_models.ArloEvent.Self","id":0,"name":"Self","namespace":"","upper_bound":"app.models.camera.arlo_models.ArloEvent","values":[],"variance":0},"slots":null,"tuple_type":null,"type_vars":[],"typeddict_type":null}},"ArloEventType":{".class":"SymbolTableNode","cross_ref":"app.models.camera.enums.ArloEventType","kind":"Gdef"},"ArloRecording":{".class":"SymbolTableNode","kind":"Gdef","node":{".class":"TypeInfo","_promote":[],"abstract_attributes":[],"alt_promote":null,"bases":["app.models.camera.mixins.TimestampMixin"],"dataclass_transform_spec":null,"declared_metaclass":null,"defn":{".class":"ClassDef","fullname":"app.models.camera.arlo_models.ArloRecording","name":"ArloRecording","type_vars":[]},"deletable_attributes":[],"deprecated":null,"flags":["fallback_to_any"],"fullname":"app.models.camera.arlo_models.ArloRecording","has_param_spec_type":false,"metaclass_type":null,"metadata":{},"module_name":"app.models.camera.arlo_models","mro":["app.models.camera.arlo_models.ArloRecording","app.models.camera.mixins.TimestampMixin","builtins.object"],"names":{".class":"SymbolTable","__table_args__":{".class":"SymbolTableNode","kind":"Mdef","node":{".class":"Var","flags":["is_initialized_in_class","is_ready","is_inferred","has_explicit_value"],"fullname":"app.models.camera.arlo_models.ArloRecording.__table_args__","name":"__table_args__","setter_type":null,"type":{".class":"TupleType","implicit":false,"items":["sqlalchemy.sql.schema.Index","sqlalchemy.sql.schema.Index","sqlalchemy.sql.schema.Index"],"partial_fallback":{".class":"Instance","args":[{".class":"AnyType","missing_import_name":null,"source_any":null,"type_of_any":6}],"extra_attrs":null,"type_ref":"builtins.tuple"}}}},"__tablename__":{".class":"SymbolTableNode","kind":"Mdef","node":{".class":"Var","flags":["is_initialized_in_class","is_ready","is_inferred","has_explicit_value"],"fullname":"app.models.camera.arlo_models.ArloRecording.__tablename__","name":"__tablename__","setter_type":null,"type":"builtins.str"}},"camera":{".class":"SymbolTableNode","kind":"Mdef","node":{".class":"Var","flags":["is_initialized_in_class","is_ready","is_inferred","has_explicit_value"],"fullname":"app.models.camera.arlo_models.ArloRecording.camera","name":"camera","setter_type":null,"type":{".class":"Instance","args":[{".class":"AnyType","missing_import_name":null,"source_any":null,"type_of_any":2}],"extra_attrs":null,"type_ref":"sqlalchemy.orm.relationships._RelationshipDeclared"}}},"camera_id":{".class":"SymbolTableNode","kind":"Mdef","node":{".class":"Var","flags":["is_initialized_in_class","is_ready","is_inferred","has_explicit_value"],"fullname":"app.models.camera.arlo_models.ArloRecording.camera_id","name":"camera_id","setter_type":null,"type":{".class":"Instance","args":["builtins.int"],"extra_attrs":null,"type_ref":"sqlalchemy.sql.schema.Column"}}},"created_date":{".class":"SymbolTableNode","kind":"Mdef","node":{".class":"Var","flags":["is_initialized_in_class","is_ready","is_inferred","has_explicit_value"],"fullname":"app.models.camera.arlo_models.ArloRecording.created_date","name":"created_date","setter_type":null,"type":{".class":"Instance","args":["datetime.datetime"],"extra_attrs":null,"type_ref":"sqlalchemy.sql.schema.Column"}}},"downloaded":{".class":"SymbolTableNode","kind":"Mdef","node":{".class":"Var","flags":["is_initialized_in_class","is_ready","is_inferred","has_explicit_value"],"fullname":"app.models.camera.arlo_models.ArloRecording.downloaded","name":"downloaded","setter_type":null,"type":{".class":"Instance","args":["builtins.bool"],"extra_attrs":null,"type_ref":"sqlalchemy.sql.schema.Column"}}},"duration":{".class":"SymbolTableNode","kind":"Mdef","node":{".class":"Var","flags":["is_initialized_in_class","is_ready","is_inferred","has_explicit_value"],"fullname":"app.models.camera.arlo_models.ArloRecording.duration","name":"duration","setter_type":null,"type":{".class":"Instance","args":["builtins.int"],"extra_attrs":null,"type_ref":"sqlalchemy.sql.schema.Column"}}},"file_size":{".class":"SymbolTableNode","kind":"Mdef","node":{".class":"Var","flags":["is_initialized_in_class","is_ready","is_inferred","has_explicit_value"],"fullname":"app.models.camera.arlo_models.ArloRecording.file_size","name":"file_size","setter_type":null,"type":{".class":"Instance","args":["builtins.int"],"extra_attrs":null,"type_ref":"sqlalchemy.sql.schema.Column"}}},"id":{".class":"SymbolTableNode","kind":"Mdef","node":{".class":"Var","flags":["is_initialized_in_class","is_ready","is_inferred","has_explicit_value"],"fullname":"app.models.camera.arlo_models.ArloRecording.id","name":"id","setter_type":null,"type":{".class":"Instance","args":["builtins.int"],"extra_attrs":null,"type_ref":"sqlalchemy.sql.schema.Column"}}},"presigned_url":{".class":"SymbolTableNode","kind":"Mdef","node":{".class":"Var","flags":["is_initialized_in_class","is_ready","is_inferred","has_explicit_value"],"fullname":"app.models.camera.arlo_models.ArloRecording.presigned_url","name":"presigned_url","setter_type":null,"type":{".class":"Instance","args":["builtins.str"],"extra_attrs":null,"type_ref":"sqlalchemy.sql.schema.Column"}}},"recording_id":{".class":"SymbolTableNode","kind":"Mdef","node":{".class":"Var","flags":["is_initialized_in_class","is_ready","is_inferred","has_explicit_value"],"fullname":"app.models.camera.arlo_models.ArloRecording.recording_id","name":"recording_id","setter_type":null,"type":{".class":"Instance","args":["builtins.str"],"extra_attrs":null,"type_ref":"sqlalchemy.sql.schema.Column"}}},"to_dict":{".class":"SymbolTableNode","kind":"Mdef","node":{".class":"FuncDef","abstract_status":0,"arg_kinds":[0],"arg_names":["self"],"dataclass_transform_spec":null,"deprecated":null,"flags":[],"fullname":"app.models.camera.arlo_models.ArloRecording.to_dict","name":"to_dict","original_first_arg":"self","type":null}}},"self_type":{".class":"TypeVarType","default":{".class":"AnyType","missing_import_name":null,"source_any":null,"type_of_any":4},"fullname":"app.models.camera.arlo_models.ArloRecording.Self","id":0,"name":"Self","namespace":"","upper_bound":"app.models.camera.arlo_models.ArloRecording","values":[],"variance":0},"slots":null,"tuple_type":null,"type_vars":[],"typeddict_type":null}},"ArloStatus":{".class":"SymbolTableNode","cross_ref":"app.models.camera.enums.ArloStatus","kind":"Gdef"},"Base":{".class":"SymbolTableNode","cross_ref":"app.models.Base","kind":"Gdef"},"BigInteger":{".class":"SymbolTableNode","cross_ref":"sqlalchemy.sql.sqltypes.BigInteger","kind":"Gdef"},"Boolean":{".class":"SymbolTableNode","cross_ref":"sqlalchemy.sql.sqltypes.Boolean","kind":"Gdef"},"Column":{".class":"SymbolTableNode","cross_ref":"sqlalchemy.sql.schema.Column","kind":"Gdef"},"DateTime":{".class":"SymbolTableNode","cross_ref":"sqlalchemy.sql.sqltypes.DateTime","kind":"Gdef"},"Enum":{".class":"SymbolTableNode","cross_ref":"sqlalchemy.sql.sqltypes.Enum","kind":"Gdef"},"ForeignKey":{".class":"SymbolTableNode","cross_ref":"sqlalchemy.sql.schema.ForeignKey","kind":"Gdef"},"Index":{".class":"SymbolTableNode","cross_ref":"sqlalchemy.sql.schema.Index","kind":"Gdef"},"Integer":{".class":"SymbolTableNode","cross_ref":"sqlalchemy.sql.sqltypes.Integer","kind":"Gdef"},"JSON":{".class":"SymbolTableNode","cross_ref":"sqlalchemy.sql.sqltypes.JSON","kind":"Gdef"},"String":{".class":"SymbolTableNode","cross_ref":"sqlalchemy.sql.sqltypes.String","kind":"Gdef"},"TimestampMixin":{".class":"SymbolTableNode","cross_ref":"app.models.camera.mixins.TimestampMixin","kind":"Gdef"},"__annotations__":{".class":"SymbolTableNode","kind":"Gdef","node":{".class":"Var","flags":["is_ready"],"fullname":"app.models.camera.arlo_models.__annotations__","name":"__annotations__","setter_type":null,"type":{".class":"Instance","args":["builtins.str",{".class":"AnyType","missing_import_name":null,"source_any":null,"type_of_any":6}],"extra_attrs":null,"type_ref":"builtins.dict"}}},"__doc__":{".class":"SymbolTableNode","kind":"Gdef","node":{".class":"Var","flags":["is_ready"],"fullname":"app.models.camera.arlo_models.__doc__","name":"__doc__","setter_type":null,"type":"builtins.str"}},"__file__":{".class":"SymbolTableNode","kind":"Gdef","node":{".class":"Var","flags":["is_ready"],"fullname":"app.models.camera.arlo_models.__file__","name":"__file__","setter_type":null,"type":"builtins.str"}},"__name__":{".class":"SymbolTableNode","kind":"Gdef","node":{".class":"Var","flags":["is_ready"],"fullname":"app.models.camera.arlo_models.__name__","name":"__name__","setter_type":null,"type":"builtins.str"}},"__package__":{".class":"SymbolTableNode","kind":"Gdef","node":{".class":"Var","flags":["is_ready"],"fullname":"app.models.camera.arlo_models.__package__","name":"__package__","setter_type":null,"type":"builtins.str"}},"__spec__":{".class":"SymbolTableNode","kind":"Gdef","node":{".class":"Var","flags":["is_ready"],"fullname":"app.models.camera.arlo_models.__spec__","name":"__spec__","setter_type":null,"type":"_frozen_importlib.ModuleSpec"}},"datetime":{".class":"SymbolTableNode","cross_ref":"datetime.datetime","kind":"Gdef"},"relationship":{".class":"SymbolTableNode","cross_ref":"sqlalchemy.orm._orm_constructors.relationship","kind":"Gdef"}},"path":"D:\\software\\app\\models\\camera\\arlo_models.py"}